setup.py
python_saucerest.egg-info/PKG-INFO
python_saucerest.egg-info/SOURCES.txt
python_saucerest.egg-info/dependency_links.txt
python_saucerest.egg-info/requires.txt
python_saucerest.egg-info/top_level.txt
saucelabs/__init__.py
saucelabs/saucerest.py