Metadata-Version: 1.0
Name: python-saucerest
Version: 0.0.3
Summary: Python wrapper around the saucelabs REST API
Home-page: https://github.com/OniOni
Author: Mathieu Sabourin
Author-email: mathieu.c.sabourin@gmail.com
License: UNKNOWN
Download-URL: https://github.com/OniOni/python-saucerest
Keywords: Sauce Labs,REST
Platform: UNKNOWN
Classifier: Development Status :: 3 - Alpha
Classifier: Intended Audience :: Developers
Classifier: License :: OSI Approved :: Apache Software License
Classifier: Natural Language :: English
Classifier: Operating System :: POSIX
Classifier: Programming Language :: Python :: 2.7
Classifier: Programming Language :: Python :: Implementation :: CPython
Classifier: Topic :: Software Development :: Libraries
